nslib/stations.py
nslib/nslib.py
nslib/nsexceptions.py
nslib/classes.py
nslib/__init__.py
nslib-0.0.2.dist-info/metadata.json
nslib-0.0.2.dist-info/top_level.txt
nslib-0.0.2.dist-info/METADATA
nslib-0.0.2.dist-info/DESCRIPTION.rst
nslib-0.0.2.dist-info/WHEEL
nslib-0.0.2.dist-info/RECORD
